pychemex/__init__.py
pychemex/compressor.py
pychemex-0.1.0.dist-info/LICENSE
pychemex-0.1.0.dist-info/METADATA
pychemex-0.1.0.dist-info/WHEEL
pychemex-0.1.0.dist-info/top_level.txt
pychemex-0.1.0.dist-info/RECORD
